setup.py
JsonToC.egg-info/PKG-INFO
JsonToC.egg-info/SOURCES.txt
JsonToC.egg-info/dependency_links.txt
JsonToC.egg-info/entry_points.txt
JsonToC.egg-info/top_level.txt
json_to_c/__init__.py
json_to_c/json_to_c.py
json_to_c/json_to_sim.py