Metadata-Version: 1.0
Name: JsonToC
Version: 1.0.3
Summary: Convert Json to C
Home-page: UNKNOWN
Author: zhaobk
Author-email: zhaobk@nationalchip.com
License: UNKNOWN
Keywords: json C
Platform: UNKNOWN
